dexter/__init__.py
dexter/framelist.py
dexter/framemap.py
dexter/helper.py
dexter/optimizer.py
dexter/readmultiple.py
dxter-0.0.1.dist-info/LICENSE.txt
dxter-0.0.1.dist-info/METADATA
dxter-0.0.1.dist-info/WHEEL
dxter-0.0.1.dist-info/top_level.txt
dxter-0.0.1.dist-info/RECORD
