Metadata-Version: 2.1
Name: dxter
Version: 0.0.1
Summary: Data Exploration Terser
Home-page: https://github.com/igormagalhaesr/dexter
Author: Igor Magalhaes
Author-email: igor.magalhaes.r@gmail.com
License: BSD 3
Platform: UNKNOWN
Classifier: Development Status :: 2 - Pre-Alpha
Classifier: License :: OSI Approved :: BSD License
Classifier: Intended Audience :: Science/Research
Classifier: Programming Language :: Python :: 3
Classifier: Programming Language :: Python :: 3 :: Only
Classifier: Programming Language :: Python :: 3.9
Classifier: Topic :: Scientific/Engineering
Classifier: Operating System :: OS Independent
Classifier: Framework :: IPython
